segtok/__init__.py
segtok/segmenter.py
segtok/segmenter_test.py
segtok/tokenizer.py
segtok/tokenizer_test.py
segtok-1.5.11.dist-info/LICENSE.txt
segtok-1.5.11.dist-info/METADATA
segtok-1.5.11.dist-info/WHEEL
segtok-1.5.11.dist-info/entry_points.txt
segtok-1.5.11.dist-info/top_level.txt
segtok-1.5.11.dist-info/RECORD
