Metadata-Version: 2.1
Name: segtok
Version: 1.5.11
Summary: sentence segmentation and word tokenization tools
Home-page: https://github.com/fnl/segtok
Author: Florian Leitner
Author-email: florian.leitner@gmail.com
License: MIT
Keywords: sentence segmenter splitter split word tokenizer token
Platform: UNKNOWN
Classifier: Development Status :: 3 - Alpha
Classifier: License :: OSI Approved :: MIT License
Classifier: Programming Language :: Python :: 2
Classifier: Programming Language :: Python :: 2.7
Classifier: Programming Language :: Python :: 3
Classifier: Programming Language :: Python :: 3.5
Classifier: Programming Language :: Python :: 3.6
Classifier: Programming Language :: Python :: 3.7
Classifier: Programming Language :: Python :: 3.8
Classifier: Topic :: Scientific/Engineering :: Information Analysis
Classifier: Topic :: Software Development :: Libraries
Classifier: Topic :: Text Processing
Classifier: Topic :: Text Processing :: Linguistic
License-File: LICENSE.txt
